deep4dream/deep_dream.py
deep4dream-0.2.2.dist-info/LICENSE
deep4dream-0.2.2.dist-info/METADATA
deep4dream-0.2.2.dist-info/WHEEL
deep4dream-0.2.2.dist-info/top_level.txt
deep4dream-0.2.2.dist-info/RECORD
