Metadata-Version: 2.1
Name: deep4dream
Version: 0.2.2
Summary: A Keras implementation of Deep Dream for any image
Home-page: https://iraqprogrammer.wordpress.com/
Author: Falah.G.Saleh
Author-email: falahgs07@gmail.com
License: UNKNOWN
Keywords: neural,artistic,neural-dream,dream,keras,neural-art,feature-visualization,machine-learning-art,ai-art,deepdream,tensorflow,inceptionv3
Platform: UNKNOWN
Classifier: Programming Language :: Python :: 3
Classifier: Programming Language :: Python :: 3.5
Classifier: Programming Language :: Python :: 3.6
Classifier: Programming Language :: Python :: 3.7
Classifier: Programming Language :: Python :: 3.8
Classifier: License :: OSI Approved :: MIT License
Classifier: Operating System :: OS Independent
Requires-Python: >=3.6
Requires-Dist: keras
Requires-Dist: scipy
